{
  "id": "f_academy",
  "name": "F.ACADEMY",
  "url": "https://www.f-academy.jp/",
  "status": "changed",
  "analyzed_at": "2026-04-15T03:25:58.512518+00:00",
  "analysis": {
    "change_nature": "受講生の声のページに新しいエピソードやインタビュー動画が追加された",
    "strategic_intent": "競合他社のF.ACADEMYが受講生の成功事例を強調してブランドイメージを向上させ、潜在的な顧客を引き付けることを目的としている",
    "business_impact": "自社のマーケティング戦略やブランドイメージに影響を与える可能性がある",
    "recommended_actions": {
      "short_term": [
        "自社の受講生の声ページを更新し、成功事例を強調する",
        "競合他社の動向を継続的にモニターする"
      ],
      "mid_term": [
        "自社のマーケティング戦略を再評価し、ブランドイメージを向上させるための新しいキャンペーンを計画する"
      ]
    },
    "threat_level": 4,
    "confidence": "high",
    "summary": "競合他社のF.ACADEMYが受講生の成功事例を強調してブランドイメージを向上させ、潜在的な顧客を引き付けることを目的としている。自社のマーケティング戦略やブランドイメージに影響を与える可能性がある。"
  }
}